Metadata-Version: 2.1
Name: telegramgetbotip
Version: 0.1.3
Summary: Python3 telegram bot to retrieve public IP of the Telegram bot's host machine.
Home-page: https://github.com/carlosplanchon/telegramgetbotip
Author: Carlos A. Planchón
Author-email: bubbledoloresuruguay2@gmail.com
License: GPL3
Download-URL: https://github.com/carlosplanchon/telegramgetbotip/archive/v0.1.3.tar.gz
Keywords: telegram,bot,ip,networking
Platform: UNKNOWN
Classifier: Intended Audience :: Developers
Classifier: Topic :: Software Development :: Build Tools
Classifier: License :: OSI Approved :: GNU General Public License v3 (GPLv3)
Classifier: Programming Language :: Python :: 3.8
